Workbook

Sheet DASHBOARD
A1: =组合信息!B1 -> XX组合
A4: 权益类资产 | C4: 收益贡献 | D4: 收益率 | E4: 沪深300指数
A5: 平均仓位 | B5: =业绩归因1!G4/100 -> 0.12266902 | C5: =业绩归因1!C4/100 -> -0.003496565 | D5: =业绩归因1!D4/100 -> -0.02850406 | E5: =组合信息!B6 -> 0.14 | G5: 权益平均
G6: =B5/SUM(B5,B8) -> 0.12030551
A7: 固收类资产 | C7: 收益贡献 | D7: 收益率 | E7: 中债综合 | G7: 仓位
A8: 平均仓位 | B8: =业绩归因1!G12/100 -> 0.89697688 | C8: =业绩归因1!C12/100 -> 0.042522242 | D8: =业绩归因1!D12/100 -> 0.047406174 | E8: =组合信息!B7 -> 0.05

Sheet 组合信息
A1: 组合信息 | B1: XX组合
A2: 组合代码 | B2: xxxxx
A3: 组合成立时间 | B3: 44201
A4: 文件数据起始区间 | B4: 45288
A5: 文件数据中止区间 | B5: 45618
A6: 区间沪深300收益率 | B6: 0.14
A7: 区间中债综合收益率 | B7: 0.05

Sheet 净值序列
A1: 数据日期 | B1: 组合收益率 | C1: 沪深300指数(收盘价) | D1: 单位净值
A2: 45289 | B2: 0 | C2: 3431.1099 | D2: 0.9934
A3: 45293 | B3: =D3/$D$2-1 -> 0.0045298973 | C3: 3386.3522 | D3: 0.9979
A4: 45294 | B4: =D4/$D$2-1 -> 0.0062411919 | C4: 3378.2971 | D4: 0.9996
A5: 45295 | B5: =D5/$D$2-1 -> 0.0073485001 | C5: 3347.0519 | D5: 1.0007
A6: 45296 | B6: =D6/$D$2-1 -> 0.0076504933 | C6: 3329.1114 | D6: 1.001
A7: 45299 | B7: =D7/$D$2-1 -> 0.0070465069 | C7: 3286.0564 | D7: 1.0004
A8: 45300 | B8: =D8/$D$2-1 -> 0.0063418563 | C8: 3292.4994 | D8: 0.9997
A9: 45301 | B9: =D9/$D$2-1 -> 0.0059391987 | C9: 3277.129 | D9: 0.9993
A10: 45302 | B10: =D10/$D$2-1 -> 0.0053352124 | C10: 3295.6717 | D10: 0.9987
A11: 45303 | B11: =D11/$D$2-1 -> 0.0070465069 | C11: 3284.1667 | D11: 1.0004
A12: 45306 | B12: =D12/$D$2-1 -> 0.0073485001 | C12: 3280.9195 | D12: 1.0007
A13: 45307 | B13: =D13/$D$2-1 -> 0.0085564727 | C13: 3300.8762 | D13: 1.0019
A14: 45308 | B14: =D14/$D$2-1 -> 0.0069458426 | C14: 3229.082 | D14: 1.0003
... A217: 45618 | B217: =D217/$D$2-1 -> 0.035433863 | C217: 3865.6989 | D217: 1.0286

Sheet 仓位序列
A1: 数据日期 | B1: 权益仓位(穿透) | C1: 沪深300指数(收盘价) | D1: 久期 | E1: 中债新综合总财富指数(收盘价) | F1: 杠杆 | G1: 成本估值占比(穿透)
A2: 45289 | B2: 0.109708 | C2: 3431.1099 | D2: 1.109417 | E2: 229.8451 | F2: 1.088781 | G2: 0.294969
A3: 45293 | B3: 0.110354 | C3: 3386.3522 | D3: 1.1001 | E3: 229.8875 | F3: 1.082539 | G3: 0.293618
A4: 45294 | B4: 0.111734 | C4: 3378.2971 | D4: 1.098719 | E4: 229.8373 | F4: 1.165698 | G4: 0.293185
A5: 45295 | B5: 0.112767 | C5: 3347.0519 | D5: 1.105436 | E5: 229.9325 | F5: 1.084181 | G5: 0.292846
A6: 45296 | B6: 0.114862 | C6: 3329.1114 | D6: 1.070871 | E6: 230.0946 | F6: 1.085708 | G6: 0.292704
A7: 45299 | B7: 0.110035 | C7: 3286.0564 | D7: 1.096804 | E7: 230.1884 | F7: 1.087473 | G7: 0.29277
A8: 45300 | B8: 0.115749 | C8: 3292.4994 | D8: 1.089224 | E8: 230.4195 | F8: 1.086502 | G8: 0.292955
A9: 45301 | B9: 0.114744 | C9: 3277.129 | D9: 1.083923 | E9: 230.4444 | F9: 1.086538 | G9: 0.293104
A10: 45302 | B10: 0.114895 | C10: 3295.6717 | D10: 1.083187 | E10: 230.4621 | F10: 1.086591 | G10: 0.293355
A11: 45303 | B11: 0.115533 | C11: 3284.1667 | D11: 1.02198 | E11: 230.4332 | F11: 1.08646 | G11: 0.292783
A12: 45306 | B12: 0.115864 | C12: 3280.9195 | D12: 1.015873 | E12: 230.4873 | F12: 1.086436 | G12: 0.2927
A13: 45307 | B13: 0.11617 | C13: 3300.8762 | D13: 1.017617 | E13: 230.4982 | F13: 1.056486 | G13: 0.292334
... A217: 45618 | B217: 0.19654 | C217: 3865.6989 | D217: 0.589669 | E217: 242.2957 | F217: 1.029036 | G217: 0.421787

Sheet 产品序列
A1: 数据日期 | B1: 权益产品 | C1: 固收产品 | D1: 流动性产品
A2: 45289 | B2: 0.109708 | C2: 0.329124 | D2: =1-B2-C2 -> 0.561168
A3: 45293 | B3: 0.110354 | C3: 0.331062 | D3: =1-B3-C3 -> 0.558584
A4: 45294 | B4: 0.111734 | C4: 0.335202 | D4: =1-B4-C4 -> 0.553064
A5: 45295 | B5: 0.112767 | C5: 0.338301 | D5: =1-B5-C5 -> 0.548932
A6: 45296 | B6: 0.114862 | C6: 0.344586 | D6: =1-B6-C6 -> 0.540552
A7: 45299 | B7: 0.110035 | C7: 0.330105 | D7: =1-B7-C7 -> 0.55986
A8: 45300 | B8: 0.115749 | C8: 0.347247 | D8: =1-B8-C8 -> 0.537004
A9: 45301 | B9: 0.114744 | C9: 0.344232 | D9: =1-B9-C9 -> 0.541024
A10: 45302 | B10: 0.114895 | C10: 0.344685 | D10: =1-B10-C10 -> 0.54042
A11: 45303 | B11: 0.115533 | C11: 0.346599 | D11: =1-B11-C11 -> 0.537868
A12: 45306 | B12: 0.115864 | C12: 0.347592 | D12: =1-B12-C12 -> 0.536544
A13: 45307 | B13: 0.11617 | C13: 0.34851 | D13: =1-B13-C13 -> 0.53532
... A217: 45618 | B217: 0.19654 | C217: 0.58962 | D217: =1-B217-C217 -> 0.21384

Sheet 权益分布行业
A1: 行业名称（申万一级） | B1: Q1 | C1: Q2 | D1: Q3 | E1: Q4 | F1: 平均持仓 | G1: 权益仓位
A2: 公用事业 | B2: 2.9219269 | C2: 3.8003823 | D2: 2.948889 | E2: 2.948889 | F2: =AVERAGE(B2:E2) -> 3.1550218 | G2: 23.210743
A3: 有色金属 | B3: 0.94899097 | C3: 4.2791576 | D3: 3.0075229 | E3: 3.0075229 | F3: =AVERAGE(B3:E3) -> 2.8107986 | G3: 26.134851
A4: 银行 | B4: 2.8502885 | C4: 2.2933359 | D4: 1.8527271 | E4: 1.8527271 | F4: =AVERAGE(B4:E4) -> 2.2122697 | G4: 14.006493
A5: 煤炭 | B5: 0.54092831 | C5: 1.9806076 | D5: 1.4694736 | E5: 1.4694736 | F5: =AVERAGE(B5:E5) -> 1.3651208 | G5: 12.096513
A6: 石油石化 | B6: 0.87144167 | C6: 1.2079136 | D6: 0.92543228 | E6: 0.92543228 | F6: =AVERAGE(B6:E6) -> 0.98255495 | G6: 7.3773028
A7: 交通运输 | B7: 0.45375194 | C7: 1.5084422 | D7: 0.93501109 | E7: 0.93501109 | F7: =AVERAGE(B7:E7) -> 0.95805408 | G7: 9.2127742
A8: 非银金融 | B8: 1.0332152 | C8: 0.044356547 | D8: 0.17440308 | E8: 0.17440308 | F8: =AVERAGE(B8:E8) -> 0.35659448 | G8: 0.27090653
A9: 环保 | B9: 0.18021681 | C9: 0.30414119 | D9: 0.20274788 | E9: 0.20274788 | F9: =AVERAGE(B9:E9) -> 0.22246344 | G9: 1.8575349
A10: 通信 | B10: 0.31632633 | C10: 0.080538304 | D10: 0.13439708 | E10: 0.13439708 | F10: =AVERAGE(B10:E10) -> 0.1664147 | G10: 0.49188574
A11: 钢铁 | B11: 0 | C11: 0.2270394 | D11: 0.14276935 | E11: 0.14276935 | F11: =AVERAGE(B11:E11) -> 0.12814452 | G11: 1.3866376
A12: 汽车 | B12: 0.0089162122 | C12: 0.41979129 | D12: 0.012081541 | E12: 0.012081541 | F12: =AVERAGE(B12:E12) -> 0.11321765 | G12: 2.5638651
A13: 国防军工 | B13: 0.042066636 | C13: 0.12158056 | D13: 0.091026503 | E13: 0.091026503 | F13: =AVERAGE(B13:E13) -> 0.086425051 | G13: 0.74255033
... A33: 其他 | B33: 0 | C33: 0 | D33: 0 | E33: 0 | F33: =AVERAGE(B33:E33) -> 0 | G33: 0

Sheet 业绩归因图
A1: 资产类别 | B1: Q1收益贡献(%) | C1: Q2收益贡献(%) | D1: Q3收益贡献(%) | E1: Q4收益贡献(%) | F1: Q1收益率(%) | G1: Q2收益率(%) | H1: Q3收益率(%) | I1: Q4收益率(%) | J1: Q1平均仓位 | K1: Q2平均仓位 | L1: Q3平均仓位 | M1: Q4平均仓位
A2: 权益类 | B2: -0.3496565 | C2: -0.3496565 | D2: -0.3496565 | E2: -0.3496565 | F2: 5 | G2: 10.620375 | H2: 18.968608 | I2: 12.266902 | J2: 5 | K2: 10.620375 | L2: 18.968608 | M2: 12.266902
A3: 固定类市值 | B3: 3.1280034 | C3: 3.1280034 | D3: 3.1280034 | E3: 3.1280034 | F3: 5.9153573 | G3: 60.773123 | H3: 39.010485 | I3: 52.879365 | J3: 5.9153573 | K3: 60.773123 | L3: 39.010485 | M3: 52.879365
A4: 固定成本类 | B4: 0.99571861 | C4: 0.99571861 | D4: 0.99571861 | E4: 0.99571861 | F4: 2.9501079 | G4: 27.755962 | H4: 41.266935 | I4: 33.751939 | J4: 2.9501079 | K4: 27.755962 | L4: 41.266935 | M4: 33.751939
A5: 货币类 | B5: 0.037941466 | C5: 0.037941466 | D5: 0.037941466 | E5: 0.037941466 | F5: 1.0893104 | G5: 1.8131961 | H5: 2.8178574 | I5: 3.483072 | J5: 1.0893104 | K5: 1.8131961 | L5: 2.8178574 | M5: 3.483072
A6: 正回购 | B6: -0.1723034 | C6: -0.1723034 | D6: -0.1723034 | E6: -0.1723034 | F6: -2.5542391 | G6: -9.5071637 | H6: -4.9222769 | I6: -6.7457821 | J6: -2.5542391 | K6: -9.5071637 | L6: -4.9222769 | M6: -6.7457821

Sheet 业绩归因1
A1: 资产大类 | B1: 资产类别 | C1: 收益贡献(%) | D1: 投资收益率(%) | E1: 投资比例(%) | H1: 投资收益(元) | I1: 资产市值(元)
E2: 组合期初 | F2: 组合期末 | G2: 组合平均 | I2: 组合期初 | J2: 组合期末 | K2: 组合平均
C3: XXXX | D3: XXXX | E3: XXXX | F3: XXXX | G3: XXXX | H3: XXXX | I3: XXXX | J3: XXXX | K3: XXXX
A4: 权益类 | B4: 权益类小计 | C4: -0.3496565 | D4: -2.850406 | E4: 10.620375 | F4: 18.968608 | G4: 12.266902 | H4: -2008012.4 | I4: 65125172 | J4: 2.07001e+08 | K4: 1.061926e+08
B5: 股票 | C5: -0.17020053 | D5: -1.4174151 | E5: 10.620375 | F5: 16.373377 | G5: 12.007811 | H5: -977430.08 | I5: 65125172 | J5: 1.7867971e+08 | K5: 1.0337294e+08
B6: 其中：新股 | C6: 0.45041718 | D6: 1355.873 | E6: 0.25788945 | F6: 0.0010069313 | G6: 0.033219717 | H6: 2586662.3 | I6: 1581403.2 | J6: 10988.46 | K6: 213014.89
B7: 股票基金 | C7: -0.1896722 | D7: -74.09159 | E7: 0 | F7: 2.3918898 | G7: 0.25599694 | H7: -1089252.3 | I7: 0 | J7: 26102262 | K7: 2785814.1
B8: 混合基金 | C8: 0.0052953077 | D8: 171.18011 | E8: 0 | F8: 0.20334199 | G8: 0.003093413 | H8: 30409.97 | I8: 0 | J8: 2219034.5 | K8: 33843.289
B9: 权益工具 | C9: 0.004920932 | D9: 0 | E9: -0.45764441 | F9: 0 | G9: -0.050255922 | H9: 28260 | I9: -2806320 | J9: 0 | K9: -306940.92
B10: 其中：港股通标的产品 | C10: -0.03730251 | D10: -113.09346 | E10: 0 | F10: 0.57686634 | G10: 0.032983792 | H10: -214221.4 | I10: 0 | J10: 6295238.4 | K10: 360801.66
B11: 外部股票型养老金 | C11: 0 | D11: 0 | E11: 0 | F11: 0 | G11: 0 | H11: 0 | I11: 0 | J11: 0 | K11: 0
A12: 固收类 | B12: 固收类小计 | C12: 4.2522242 | D12: 4.7406174 | E12: 95.083287 | F12: 81.22438 | G12: 89.697688 | H12: 24419735 | I12: 5.8305996e+08 | J12: 8.8638702e+08 | K12: 7.1578713e+08
B13: 固定类市值总计 | C13: 3.1280034 | D13: 5.9153573 | E13: 60.773123 | F13: 39.010485 | G13: 52.879365 | H13: 17963543 | I13: 3.7266669e+08 | J13: 4.2571439e+08 | K13: 4.1892947e+08
B14: 企业债 | C14: 1.0407111 | D14: 5.3529506 | E14: 29.636393 | F14: 11.519667 | G14: 19.441821 | H14: 5976610.7 | I14: 1.8173324e+08 | J14: 1.2571205e+08 | K14: 1.4715706e+08
B15: 中期票据 | C15: 0.021572353 | D15: 3.0831223 | E15: 0.0078491161 | F15: 1.7885509 | G15: 0.69969176 | H15: 123886.02 | I15: 48131.543 | J15: 19518133 | K15: 7013800
B16: 短期融资券 | C16: 0.0040809617 | D16: 3.114018 | E16: 0 | F16: 0.056074503 | G16: 0.13105132 | H16: 23436.206 | I16: 0 | J16: 611930.95 | K16: 1282033.4
B17: 可转债 | C17: 1.0766013 | D17: 8.6909761 | E17: 14.756712 | F17: 8.8568566 | G17: 12.387576 | H17: 6182721.5 | I17: 90489591 | J17: 96653280 | K17: 96663014
B18: 金融债 | C18: 0.56786421 | D18: 4.881919 | E18: 6.1170867 | F18: 14.349191 | G18: 11.631988 | H18: 3261138.9 | I18: 37510570 | J18: 1.5659013e+08 | K18: 1.011844e+08
B19: 债券基金 | C19: 0.20775684 | D19: 6.6518655 | E19: 3.40732 | F19: 0.79361665 | G19: 3.1232869 | H19: 1193109 | I19: 20894018 | J19: 8660595.5 | K19: 23905691
B20: 次级债 | C20: 0 | D20: 0 | E20: 0 | F20: 0 | G20: 0 | H20: 0 | I20: 0 | J20: 0 | K20: 0
B21: 国债 | C21: 0.21038069 | D21: 3.8503403 | E21: 6.8477621 | F21: 1.6465282 | G21: 5.4639506 | H21: 1208177.3 | I21: 41991143 | J21: 17968265 | K21: 41723473
B22: 其他市值类 | C22: -0.00096402366 | D22: 0 | E22: 0 | F22: 0 | G22: -0.07998775 | H22: -5536.2091 | I22: 0 | J22: 0 | K22: -571591.29
B23: 固定成本类合计 | C23: 0.99571861 | D23: 2.9501079 | E23: 27.755962 | F23: 41.266935 | G23: 33.751939 | H23: 5718227.3 | I23: 1.7020226e+08 | J23: 4.5033863e+08 | K23: 2.7599205e+08
B24: PPN | C24: 3.1004548e-05 | D24: 6.3728771 | E24: 0 | F24: 0.0083700486 | G24: 0.00048650786 | H24: 178.05337 | I24: 0 | J24: 91340.832 | K24: 5329.0019
... B31: 外部固收型养老金 | C31: 0.12850224 | D31: 4.1906768 | E31: 6.5542019 | F31: 0.94695965 | G31: 3.0663839 | H31: 737964.53 | I31: 40191003 | J31: 10334000 | K31: 20865602
A32: 货币类 | B32: 货币类小计 | C32: 0.037941466 | D32: 1.0893104 | E32: 1.8131961 | F32: 2.8178574 | G32: 3.483072 | H32: 217890.8 | I32: 11118695 | J32: 30750770 | K32: 27297506
B33: 活期存款 | C33: 0.0032808597 | D33: 0.26403452 | E33: 0.095478161 | F33: 1.0243164 | G33: 1.2425874 | H33: 18841.369 | I33: 585481.36 | J33: 11178181 | K33: 9771129
B34: 中央银行票据 | C34: 0 | D34: 0 | E34: 0 | F34: 0 | G34: 0 | H34: 0 | I34: 0 | J34: 0 | K34: 0
B35: 一年期以内的银行存款 | C35: 0 | D35: 0 | E35: 0 | F35: 0 | G35: 0 | H35: 0 | I35: 0 | J35: 0 | K35: 0
B36: 货币市场基金 | C36: 1.3294466e-05 | D36: 1.5486787 | E36: 0 | F36: 0.093941321 | G36: 0.00085843927 | H36: 76.347656 | I36: 0 | J36: 1025164.7 | K36: 9396.0063
B37: 债券回购 | C37: 0.016388072 | D37: 3.5849172 | E37: 0 | F37: 0.28539441 | G37: 0.45713948 | H37: 94113.658 | I37: 0 | J37: 3114457.7 | K37: 3917663
B38: 证券清算款 | C38: 0 | D38: 0 | E38: 0.75026371 | F38: 0.88092344 | G38: 0.92991882 | H38: 0 | I38: 4600690 | J38: 9613358.7 | K38: 7004698.2
B39: 清算备付金 | C39: 0.01825924 | D39: 2.1416758 | E39: 0.96745421 | F39: 0.53328184 | G39: 0.85256785 | H39: 104859.43 | I39: 5932523.2 | J39: 5819608.6 | K39: 6594619.8
A40: 其他类 | B40: 其他 | C40: 0.004710433 | D40: 0.23068756 | E40: 2.1550755 | F40: 2.377745 | G40: 2.0419103 | H40: 27051.143 | I40: 13215132 | J40: 25947902 | K40: 16452670
A41: 负债类 | B41: 负债类小计 | C41: -0.75501097 | D41: -10.080829 | E41: -9.6719332 | F41: -5.3885905 | G41: -7.489572 | H41: -4335888 | I41: -59309234 | J41: -58804716 | K41: -59066654
B42: 正回购 | C42: -0.1723034 | D42: -2.5542391 | E42: -9.5071637 | F42: -4.9222769 | G42: -6.7457821 | H42: -989506.5 | I42: -58298852 | J42: -53715921 | K42: -53064109
B43: 各类费用 | C43: -0.58270757 | D43: -78.343032 | E43: -0.16476954 | F43: -0.46631352 | G43: -0.74378992 | H43: -3346381.5 | I43: -1010382.8 | J43: -5088795.4 | K43: -6002544.9
A44: 合计 | B44: 合计 | C44: 3.1902087 | D44: 3.1902087 | E44: 100 | F44: 100 | G44: 100 | H44: 18320777 | I44: 6.1320972e+08 | J44: 1.091282e+09 | K44: 8.0666325e+08

Sheet 业绩归因2
A1: 资产大类 | B1: 资产类别 | C1: 收益贡献(%) | D1: 投资收益率(%) | E1: 投资比例(%) | H1: 投资收益(元) | I1: 资产市值(元)
E2: 组合期初 | F2: 组合期末 | G2: 组合平均 | I2: 组合期初 | J2: 组合期末 | K2: 组合平均
C3: XXXX | D3: XXXX | E3: XXXX | F3: XXXX | G3: XXXX | H3: XXXX | I3: XXXX | J3: XXXX | K3: XXXX
A4: 权益类 | B4: 权益类小计 | C4: -0.3496565 | D4: -2.850406 | E4: 10.620375 | F4: 18.968608 | G4: 12.266902 | H4: -2008012.4 | I4: 65125172 | J4: 2.07001e+08 | K4: 1.061926e+08
B5: 股票 | C5: -0.17020053 | D5: -1.4174151 | E5: 10.620375 | F5: 16.373377 | G5: 12.007811 | H5: -977430.08 | I5: 65125172 | J5: 1.7867971e+08 | K5: 1.0337294e+08
B6: 其中：新股 | C6: 0.45041718 | D6: 1355.873 | E6: 0.25788945 | F6: 0.0010069313 | G6: 0.033219717 | H6: 2586662.3 | I6: 1581403.2 | J6: 10988.46 | K6: 213014.89
B7: 股票基金 | C7: -0.1896722 | D7: -74.09159 | E7: 0 | F7: 2.3918898 | G7: 0.25599694 | H7: -1089252.3 | I7: 0 | J7: 26102262 | K7: 2785814.1
B8: 混合基金 | C8: 0.0052953077 | D8: 171.18011 | E8: 0 | F8: 0.20334199 | G8: 0.003093413 | H8: 30409.97 | I8: 0 | J8: 2219034.5 | K8: 33843.289
B9: 权益工具 | C9: 0.004920932 | D9: 0 | E9: -0.45764441 | F9: 0 | G9: -0.050255922 | H9: 28260 | I9: -2806320 | J9: 0 | K9: -306940.92
B10: 其中：港股通标的产品 | C10: -0.03730251 | D10: -113.09346 | E10: 0 | F10: 0.57686634 | G10: 0.032983792 | H10: -214221.4 | I10: 0 | J10: 6295238.4 | K10: 360801.66
B11: 外部股票型养老金 | C11: 0 | D11: 0 | E11: 0 | F11: 0 | G11: 0 | H11: 0 | I11: 0 | J11: 0 | K11: 0
A12: 固收类 | B12: 固收类小计 | C12: 4.2522242 | D12: 4.7406174 | E12: 95.083287 | F12: 81.22438 | G12: 89.697688 | H12: 24419735 | I12: 5.8305996e+08 | J12: 8.8638702e+08 | K12: 7.1578713e+08
B13: 固定类市值总计 | C13: 3.1280034 | D13: 5.9153573 | E13: 60.773123 | F13: 39.010485 | G13: 52.879365 | H13: 17963543 | I13: 3.7266669e+08 | J13: 4.2571439e+08 | K13: 4.1892947e+08
B14: 企业债 | C14: 1.0407111 | D14: 5.3529506 | E14: 29.636393 | F14: 11.519667 | G14: 19.441821 | H14: 5976610.7 | I14: 1.8173324e+08 | J14: 1.2571205e+08 | K14: 1.4715706e+08
B15: 中期票据 | C15: 0.021572353 | D15: 3.0831223 | E15: 0.0078491161 | F15: 1.7885509 | G15: 0.69969176 | H15: 123886.02 | I15: 48131.543 | J15: 19518133 | K15: 7013800
B16: 短期融资券 | C16: 0.0040809617 | D16: 3.114018 | E16: 0 | F16: 0.056074503 | G16: 0.13105132 | H16: 23436.206 | I16: 0 | J16: 611930.95 | K16: 1282033.4
B17: 可转债 | C17: 1.0766013 | D17: 8.6909761 | E17: 14.756712 | F17: 8.8568566 | G17: 12.387576 | H17: 6182721.5 | I17: 90489591 | J17: 96653280 | K17: 96663014
B18: 金融债 | C18: 0.56786421 | D18: 4.881919 | E18: 6.1170867 | F18: 14.349191 | G18: 11.631988 | H18: 3261138.9 | I18: 37510570 | J18: 1.5659013e+08 | K18: 1.011844e+08
B19: 债券基金 | C19: 0.20775684 | D19: 6.6518655 | E19: 3.40732 | F19: 0.79361665 | G19: 3.1232869 | H19: 1193109 | I19: 20894018 | J19: 8660595.5 | K19: 23905691
B20: 次级债 | C20: 0 | D20: 0 | E20: 0 | F20: 0 | G20: 0 | H20: 0 | I20: 0 | J20: 0 | K20: 0
B21: 国债 | C21: 0.21038069 | D21: 3.8503403 | E21: 6.8477621 | F21: 1.6465282 | G21: 5.4639506 | H21: 1208177.3 | I21: 41991143 | J21: 17968265 | K21: 41723473
B22: 其他市值类 | C22: -0.00096402366 | D22: 0 | E22: 0 | F22: 0 | G22: -0.07998775 | H22: -5536.2091 | I22: 0 | J22: 0 | K22: -571591.29
B23: 固定成本类合计 | C23: 0.99571861 | D23: 2.9501079 | E23: 27.755962 | F23: 41.266935 | G23: 33.751939 | H23: 5718227.3 | I23: 1.7020226e+08 | J23: 4.5033863e+08 | K23: 2.7599205e+08
B24: PPN | C24: 3.1004548e-05 | D24: 6.3728771 | E24: 0 | F24: 0.0083700486 | G24: 0.00048650786 | H24: 178.05337 | I24: 0 | J24: 91340.832 | K24: 5329.0019
... B31: 外部固收型养老金 | C31: 0.12850224 | D31: 4.1906768 | E31: 6.5542019 | F31: 0.94695965 | G31: 3.0663839 | H31: 737964.53 | I31: 40191003 | J31: 10334000 | K31: 20865602
A32: 货币类 | B32: 货币类小计 | C32: 0.037941466 | D32: 1.0893104 | E32: 1.8131961 | F32: 2.8178574 | G32: 3.483072 | H32: 217890.8 | I32: 11118695 | J32: 30750770 | K32: 27297506
B33: 活期存款 | C33: 0.0032808597 | D33: 0.26403452 | E33: 0.095478161 | F33: 1.0243164 | G33: 1.2425874 | H33: 18841.369 | I33: 585481.36 | J33: 11178181 | K33: 9771129
B34: 中央银行票据 | C34: 0 | D34: 0 | E34: 0 | F34: 0 | G34: 0 | H34: 0 | I34: 0 | J34: 0 | K34: 0
B35: 一年期以内的银行存款 | C35: 0 | D35: 0 | E35: 0 | F35: 0 | G35: 0 | H35: 0 | I35: 0 | J35: 0 | K35: 0
B36: 货币市场基金 | C36: 1.3294466e-05 | D36: 1.5486787 | E36: 0 | F36: 0.093941321 | G36: 0.00085843927 | H36: 76.347656 | I36: 0 | J36: 1025164.7 | K36: 9396.0063
B37: 债券回购 | C37: 0.016388072 | D37: 3.5849172 | E37: 0 | F37: 0.28539441 | G37: 0.45713948 | H37: 94113.658 | I37: 0 | J37: 3114457.7 | K37: 3917663
B38: 证券清算款 | C38: 0 | D38: 0 | E38: 0.75026371 | F38: 0.88092344 | G38: 0.92991882 | H38: 0 | I38: 4600690 | J38: 9613358.7 | K38: 7004698.2
B39: 清算备付金 | C39: 0.01825924 | D39: 2.1416758 | E39: 0.96745421 | F39: 0.53328184 | G39: 0.85256785 | H39: 104859.43 | I39: 5932523.2 | J39: 5819608.6 | K39: 6594619.8
A40: 其他类 | B40: 其他 | C40: 0.004710433 | D40: 0.23068756 | E40: 2.1550755 | F40: 2.377745 | G40: 2.0419103 | H40: 27051.143 | I40: 13215132 | J40: 25947902 | K40: 16452670
A41: 负债类 | B41: 负债类小计 | C41: -0.75501097 | D41: -10.080829 | E41: -9.6719332 | F41: -5.3885905 | G41: -7.489572 | H41: -4335888 | I41: -59309234 | J41: -58804716 | K41: -59066654
B42: 正回购 | C42: -0.1723034 | D42: -2.5542391 | E42: -9.5071637 | F42: -4.9222769 | G42: -6.7457821 | H42: -989506.5 | I42: -58298852 | J42: -53715921 | K42: -53064109
B43: 各类费用 | C43: -0.58270757 | D43: -78.343032 | E43: -0.16476954 | F43: -0.46631352 | G43: -0.74378992 | H43: -3346381.5 | I43: -1010382.8 | J43: -5088795.4 | K43: -6002544.9
A44: 合计 | B44: 合计 | C44: 3.1902087 | D44: 3.1902087 | E44: 100 | F44: 100 | G44: 100 | H44: 18320777 | I44: 6.1320972e+08 | J44: 1.091282e+09 | K44: 8.0666325e+08
